anon_notepad-0.2.0.dist-info/licenses/LICENSE
noti/__init__.py
noti/generator.py
anon_notepad-0.2.0.dist-info/METADATA
anon_notepad-0.2.0.dist-info/WHEEL
anon_notepad-0.2.0.dist-info/entry_points.txt
anon_notepad-0.2.0.dist-info/top_level.txt
anon_notepad-0.2.0.dist-info/RECORD
